{
    "datataulukko":[
     {
      "Time": "1850",
      "Anomaly (deg C)": "-0.41765878",
      "Lower confidence limit (2.5%)": "-0.589203",
      "Upper confidence limit (97,5%)": "-0.24611452"
     },
     {
      "Time": "1851",
      "Anomaly (deg C)": "-0.2333498",
      "Lower confidence limit (2.5%)": "-0.41186792",
      "Upper confidence limit (97,5%)": "-0.054831687"
     },
     {
      "Time": "1852",
      "Anomaly (deg C)": "-0.22939907",
      "Lower confidence limit (2.5%)": "-0.40938243",
      "Upper confidence limit (97,5%)": "-0.04941572"
     },
     {
      "Time": "1853",
      "Anomaly (deg C)": "-0.27035445",
      "Lower confidence limit (2.5%)": "-0.43000934",
      "Upper confidence limit (97,5%)": "-0.110699534"
     },
     {
      "Time": "1854",
      "Anomaly (deg C)": "-0.29163003",
      "Lower confidence limit (2.5%)": "-0.43282393",
      "Upper confidence limit (97,5%)": "-0.15043613"
     },
     {
      "Time": "1855",
      "Anomaly (deg C)": "-0.2969512",
      "Lower confidence limit (2.5%)": "-0.43935776",
      "Upper confidence limit (97,5%)": "-0.15454465"
     },
     {
      "Time": "1856",
      "Anomaly (deg C)": "-0.32035372",
      "Lower confidence limit (2.5%)": "-0.46809322",
      "Upper confidence limit (97,5%)": "-0.1726142"
     },
     {
      "Time": "1857",
      "Anomaly (deg C)": "-0.46723005",
      "Lower confidence limit (2.5%)": "-0.61632216",
      "Upper confidence limit (97,5%)": "-0.31813794"
     },
     {
      "Time": "1858",
      "Anomaly (deg C)": "-0.3887657",
      "Lower confidence limit (2.5%)": "-0.53688604",
      "Upper confidence limit (97,5%)": "-0.24064532"
     },
     {
      "Time": "1859",
      "Anomaly (deg C)": "-0.28119546",
      "Lower confidence limit (2.5%)": "-0.42384982",
      "Upper confidence limit (97,5%)": "-0.13854107"
     },
     {
      "Time": "1860",
      "Anomaly (deg C)": "-0.39016518",
      "Lower confidence limit (2.5%)": "-0.5389766",
      "Upper confidence limit (97,5%)": "-0.24135375"
     },
     {
      "Time": "1861",
      "Anomaly (deg C)": "-0.42927712",
      "Lower confidence limit (2.5%)": "-0.5972301",
      "Upper confidence limit (97,5%)": "-0.26132414"
     },
     {
      "Time": "1862",
      "Anomaly (deg C)": "-0.53639776",
      "Lower confidence limit (2.5%)": "-0.7037096",
      "Upper confidence limit (97,5%)": "-0.36908585"
     },
     {
      "Time": "1863",
      "Anomaly (deg C)": "-0.3443432",
      "Lower confidence limit (2.5%)": "-0.5341645",
      "Upper confidence limit (97,5%)": "-0.1545219"
     },
     {
      "Time": "1864",
      "Anomaly (deg C)": "-0.4654367",
      "Lower confidence limit (2.5%)": "-0.6480974",
      "Upper confidence limit (97,5%)": "-0.282776"
     },
     {
      "Time": "1865",
      "Anomaly (deg C)": "-0.33258784",
      "Lower confidence limit (2.5%)": "-0.5246526",
      "Upper confidence limit (97,5%)": "-0.14052312"
     },
     {
      "Time": "1866",
      "Anomaly (deg C)": "-0.34126064",
      "Lower confidence limit (2.5%)": "-0.52183825",
      "Upper confidence limit (97,5%)": "-0.16068307"
     },
     {
      "Time": "1867",
      "Anomaly (deg C)": "-0.35696334",
      "Lower confidence limit (2.5%)": "-0.55306214",
      "Upper confidence limit (97,5%)": "-0.16086453"
     },
     {
      "Time": "1868",
      "Anomaly (deg C)": "-0.35196072",
      "Lower confidence limit (2.5%)": "-0.52965826",
      "Upper confidence limit (97,5%)": "-0.17426313"
     },
     {
      "Time": "1869",
      "Anomaly (deg C)": "-0.31657043",
      "Lower confidence limit (2.5%)": "-0.47642276",
      "Upper confidence limit (97,5%)": "-0.15671812"
     },
     {
      "Time": "1870",
      "Anomaly (deg C)": "-0.32789087",
      "Lower confidence limit (2.5%)": "-0.46867347",
      "Upper confidence limit (97,5%)": "-0.18710826"
     },
     {
      "Time": "1871",
      "Anomaly (deg C)": "-0.3685807",
      "Lower confidence limit (2.5%)": "-0.5141493",
      "Upper confidence limit (97,5%)": "-0.22301209"
     },
     {
      "Time": "1872",
      "Anomaly (deg C)": "-0.32804197",
      "Lower confidence limit (2.5%)": "-0.4630833",
      "Upper confidence limit (97,5%)": "-0.19300064"
     },
     {
      "Time": "1873",
      "Anomaly (deg C)": "-0.34133235",
      "Lower confidence limit (2.5%)": "-0.4725396",
      "Upper confidence limit (97,5%)": "-0.21012507"
     },
     {
      "Time": "1874",
      "Anomaly (deg C)": "-0.3732512",
      "Lower confidence limit (2.5%)": "-0.5071426",
      "Upper confidence limit (97,5%)": "-0.2393598"
     },
     {
      "Time": "1875",
      "Anomaly (deg C)": "-0.37562594",
      "Lower confidence limit (2.5%)": "-0.514041",
      "Upper confidence limit (97,5%)": "-0.23721085"
     },
     {
      "Time": "1876",
      "Anomaly (deg C)": "-0.42410994",
      "Lower confidence limit (2.5%)": "-0.56287116",
      "Upper confidence limit (97,5%)": "-0.28534868"
     },
     {
      "Time": "1877",
      "Anomaly (deg C)": "-0.101108834",
      "Lower confidence limit (2.5%)": "-0.22982001",
      "Upper confidence limit (97,5%)": "0.027602348"
     },
     {
      "Time": "1878",
      "Anomaly (deg C)": "-0.011315193",
      "Lower confidence limit (2.5%)": "-0.13121258",
      "Upper confidence limit (97,5%)": "0.10858219"
     },
     {
      "Time": "1879",
      "Anomaly (deg C)": "-0.30363432",
      "Lower confidence limit (2.5%)": "-0.43406433",
      "Upper confidence limit (97,5%)": "-0.1732043"
     },
     {
      "Time": "1880",
      "Anomaly (deg C)": "-0.31583208",
      "Lower confidence limit (2.5%)": "-0.44015095",
      "Upper confidence limit (97,5%)": "-0.19151321"
     },
     {
      "Time": "1881",
      "Anomaly (deg C)": "-0.23224552",
      "Lower confidence limit (2.5%)": "-0.35793498",
      "Upper confidence limit (97,5%)": "-0.10655605"
     },
     {
      "Time": "1882",
      "Anomaly (deg C)": "-0.29553008",
      "Lower confidence limit (2.5%)": "-0.4201501",
      "Upper confidence limit (97,5%)": "-0.17091006"
     },
     {
      "Time": "1883",
      "Anomaly (deg C)": "-0.3464744",
      "Lower confidence limit (2.5%)": "-0.4608177",
      "Upper confidence limit (97,5%)": "-0.23213111"
     },
     {
      "Time": "1884",
      "Anomaly (deg C)": "-0.49232006",
      "Lower confidence limit (2.5%)": "-0.6026686",
      "Upper confidence limit (97,5%)": "-0.38197154"
     },
     {
      "Time": "1885",
      "Anomaly (deg C)": "-0.47112358",
      "Lower confidence limit (2.5%)": "-0.5830682",
      "Upper confidence limit (97,5%)": "-0.35917896"
     },
     {
      "Time": "1886",
      "Anomaly (deg C)": "-0.42090362",
      "Lower confidence limit (2.5%)": "-0.5225382",
      "Upper confidence limit (97,5%)": "-0.31926903"
     },
     {
      "Time": "1887",
      "Anomaly (deg C)": "-0.49878576",
      "Lower confidence limit (2.5%)": "-0.61655986",
      "Upper confidence limit (97,5%)": "-0.3810117"
     },
     {
      "Time": "1888",
      "Anomaly (deg C)": "-0.37937889",
      "Lower confidence limit (2.5%)": "-0.49332377",
      "Upper confidence limit (97,5%)": "-0.265434"
     },
     {
      "Time": "1889",
      "Anomaly (deg C)": "-0.24989556",
      "Lower confidence limit (2.5%)": "-0.37222093",
      "Upper confidence limit (97,5%)": "-0.12757017"
     },
     {
      "Time": "1890",
      "Anomaly (deg C)": "-0.50685817",
      "Lower confidence limit (2.5%)": "-0.6324095",
      "Upper confidence limit (97,5%)": "-0.3813068"
     },
     {
      "Time": "1891",
      "Anomaly (deg C)": "-0.40131494",
      "Lower confidence limit (2.5%)": "-0.5373699",
      "Upper confidence limit (97,5%)": "-0.26525995"
     },
     {
      "Time": "1892",
      "Anomaly (deg C)": "-0.5075585",
      "Lower confidence limit (2.5%)": "-0.64432853",
      "Upper confidence limit (97,5%)": "-0.3707885"
     },
     {
      "Time": "1893",
      "Anomaly (deg C)": "-0.49461925",
      "Lower confidence limit (2.5%)": "-0.6315314",
      "Upper confidence limit (97,5%)": "-0.35770702"
     },
     {
      "Time": "1894",
      "Anomaly (deg C)": "-0.48376393",
      "Lower confidence limit (2.5%)": "-0.6255681",
      "Upper confidence limit (97,5%)": "-0.34195974"
     },
     {
      "Time": "1895",
      "Anomaly (deg C)": "-0.4487516",
      "Lower confidence limit (2.5%)": "-0.58202064",
      "Upper confidence limit (97,5%)": "-0.3154826"
     },
     {
      "Time": "1896",
      "Anomaly (deg C)": "-0.28400728",
      "Lower confidence limit (2.5%)": "-0.4174015",
      "Upper confidence limit (97,5%)": "-0.15061308"
     },
     {
      "Time": "1897",
      "Anomaly (deg C)": "-0.25980017",
      "Lower confidence limit (2.5%)": "-0.39852425",
      "Upper confidence limit (97,5%)": "-0.12107607"
     },
     {
      "Time": "1898",
      "Anomaly (deg C)": "-0.48579213",
      "Lower confidence limit (2.5%)": "-0.6176492",
      "Upper confidence limit (97,5%)": "-0.35393503"
     },
     {
      "Time": "1899",
      "Anomaly (deg C)": "-0.35543364",
      "Lower confidence limit (2.5%)": "-0.48639694",
      "Upper confidence limit (97,5%)": "-0.22447036"
     },
     {
      "Time": "1900",
      "Anomaly (deg C)": "-0.23447904",
      "Lower confidence limit (2.5%)": "-0.3669676",
      "Upper confidence limit (97,5%)": "-0.10199049"
     },
     {
      "Time": "1901",
      "Anomaly (deg C)": "-0.29342857",
      "Lower confidence limit (2.5%)": "-0.42967388",
      "Upper confidence limit (97,5%)": "-0.15718324"
     },
     {
      "Time": "1902",
      "Anomaly (deg C)": "-0.43898427",
      "Lower confidence limit (2.5%)": "-0.5754281",
      "Upper confidence limit (97,5%)": "-0.30254042"
     },
     {
      "Time": "1903",
      "Anomaly (deg C)": "-0.5333264",
      "Lower confidence limit (2.5%)": "-0.66081935",
      "Upper confidence limit (97,5%)": "-0.40583345"
     },
     {
      "Time": "1904",
      "Anomaly (deg C)": "-0.5975614",
      "Lower confidence limit (2.5%)": "-0.7288325",
      "Upper confidence limit (97,5%)": "-0.46629035"
     },
     {
      "Time": "1905",
      "Anomaly (deg C)": "-0.40775132",
      "Lower confidence limit (2.5%)": "-0.5350291",
      "Upper confidence limit (97,5%)": "-0.28047356"
     },
     {
      "Time": "1906",
      "Anomaly (deg C)": "-0.3191393",
      "Lower confidence limit (2.5%)": "-0.45052385",
      "Upper confidence limit (97,5%)": "-0.18775477"
     },
     {
      "Time": "1907",
      "Anomaly (deg C)": "-0.5041577",
      "Lower confidence limit (2.5%)": "-0.6262818",
      "Upper confidence limit (97,5%)": "-0.38203365"
     },
     {
      "Time": "1908",
      "Anomaly (deg C)": "-0.5138707",
      "Lower confidence limit (2.5%)": "-0.63748026",
      "Upper confidence limit (97,5%)": "-0.3902612"
     },
     {
      "Time": "1909",
      "Anomaly (deg C)": "-0.5357649",
      "Lower confidence limit (2.5%)": "-0.6526296",
      "Upper confidence limit (97,5%)": "-0.41890016"
     },
     {
      "Time": "1910",
      "Anomaly (deg C)": "-0.5310242",
      "Lower confidence limit (2.5%)": "-0.6556868",
      "Upper confidence limit (97,5%)": "-0.40636164"
     },
     {
      "Time": "1911",
      "Anomaly (deg C)": "-0.5392051",
      "Lower confidence limit (2.5%)": "-0.66223973",
      "Upper confidence limit (97,5%)": "-0.4161705"
     },
     {
      "Time": "1912",
      "Anomaly (deg C)": "-0.47567302",
      "Lower confidence limit (2.5%)": "-0.5893311",
      "Upper confidence limit (97,5%)": "-0.36201498"
     },
     {
      "Time": "1913",
      "Anomaly (deg C)": "-0.46715254",
      "Lower confidence limit (2.5%)": "-0.5893755",
      "Upper confidence limit (97,5%)": "-0.34492958"
     },
     {
      "Time": "1914",
      "Anomaly (deg C)": "-0.2625924",
      "Lower confidence limit (2.5%)": "-0.38276345",
      "Upper confidence limit (97,5%)": "-0.1424214"
     },
     {
      "Time": "1915",
      "Anomaly (deg C)": "-0.19184391",
      "Lower confidence limit (2.5%)": "-0.32196194",
      "Upper confidence limit (97,5%)": "-0.06172589"
     },
     {
      "Time": "1916",
      "Anomaly (deg C)": "-0.42020997",
      "Lower confidence limit (2.5%)": "-0.5588941",
      "Upper confidence limit (97,5%)": "-0.28152588"
     },
     {
      "Time": "1917",
      "Anomaly (deg C)": "-0.54301953",
      "Lower confidence limit (2.5%)": "-0.6921192",
      "Upper confidence limit (97,5%)": "-0.3939199"
     },
     {
      "Time": "1918",
      "Anomaly (deg C)": "-0.42458433",
      "Lower confidence limit (2.5%)": "-0.58198184",
      "Upper confidence limit (97,5%)": "-0.26718682"
     },
     {
      "Time": "1919",
      "Anomaly (deg C)": "-0.32551822",
      "Lower confidence limit (2.5%)": "-0.48145813",
      "Upper confidence limit (97,5%)": "-0.1695783"
     },
     {
      "Time": "1920",
      "Anomaly (deg C)": "-0.2985808",
      "Lower confidence limit (2.5%)": "-0.44860035",
      "Upper confidence limit (97,5%)": "-0.14856121"
     },
     {
      "Time": "1921",
      "Anomaly (deg C)": "-0.24067703",
      "Lower confidence limit (2.5%)": "-0.38175339",
      "Upper confidence limit (97,5%)": "-0.09960067"
     },
     {
      "Time": "1922",
      "Anomaly (deg C)": "-0.33922812",
      "Lower confidence limit (2.5%)": "-0.46610323",
      "Upper confidence limit (97,5%)": "-0.21235302"
     },
     {
      "Time": "1923",
      "Anomaly (deg C)": "-0.31793055",
      "Lower confidence limit (2.5%)": "-0.444173",
      "Upper confidence limit (97,5%)": "-0.1916881"
     },
     {
      "Time": "1924",
      "Anomaly (deg C)": "-0.3120622",
      "Lower confidence limit (2.5%)": "-0.4388317",
      "Upper confidence limit (97,5%)": "-0.18529275"
     },
     {
      "Time": "1925",
      "Anomaly (deg C)": "-0.28242525",
      "Lower confidence limit (2.5%)": "-0.4147755",
      "Upper confidence limit (97,5%)": "-0.15007503"
     },
     {
      "Time": "1926",
      "Anomaly (deg C)": "-0.12283547",
      "Lower confidence limit (2.5%)": "-0.25264767",
      "Upper confidence limit (97,5%)": "0.006976739"
     },
     {
      "Time": "1927",
      "Anomaly (deg C)": "-0.22940508",
      "Lower confidence limit (2.5%)": "-0.35135695",
      "Upper confidence limit (97,5%)": "-0.10745319"
     },
     {
      "Time": "1928",
      "Anomaly (deg C)": "-0.20676155",
      "Lower confidence limit (2.5%)": "-0.33881804",
      "Upper confidence limit (97,5%)": "-0.074705064"
     },
     {
      "Time": "1929",
      "Anomaly (deg C)": "-0.39275664",
      "Lower confidence limit (2.5%)": "-0.52656746",
      "Upper confidence limit (97,5%)": "-0.25894582"
     },
     {
      "Time": "1930",
      "Anomaly (deg C)": "-0.1768054",
      "Lower confidence limit (2.5%)": "-0.29041144",
      "Upper confidence limit (97,5%)": "-0.06319936"
     },
     {
      "Time": "1931",
      "Anomaly (deg C)": "-0.10339768",
      "Lower confidence limit (2.5%)": "-0.2126916",
      "Upper confidence limit (97,5%)": "0.0058962475"
     },
     {
      "Time": "1932",
      "Anomaly (deg C)": "-0.14546166",
      "Lower confidence limit (2.5%)": "-0.25195515",
      "Upper confidence limit (97,5%)": "-0.0389682"
     },
     {
      "Time": "1933",
      "Anomaly (deg C)": "-0.32234442",
      "Lower confidence limit (2.5%)": "-0.4271004",
      "Upper confidence limit (97,5%)": "-0.21758842"
     },
     {
      "Time": "1934",
      "Anomaly (deg C)": "-0.17433685",
      "Lower confidence limit (2.5%)": "-0.27400395",
      "Upper confidence limit (97,5%)": "-0.07466974"
     },
     {
      "Time": "1935",
      "Anomaly (deg C)": "-0.20605922",
      "Lower confidence limit (2.5%)": "-0.30349734",
      "Upper confidence limit (97,5%)": "-0.10862111"
     },
     {
      "Time": "1936",
      "Anomaly (deg C)": "-0.16952093",
      "Lower confidence limit (2.5%)": "-0.26351926",
      "Upper confidence limit (97,5%)": "-0.07552261"
     },
     {
      "Time": "1937",
      "Anomaly (deg C)": "-0.01919893",
      "Lower confidence limit (2.5%)": "-0.11975875",
      "Upper confidence limit (97,5%)": "0.08136089"
     },
     {
      "Time": "1938",
      "Anomaly (deg C)": "-0.012200732",
      "Lower confidence limit (2.5%)": "-0.11030374",
      "Upper confidence limit (97,5%)": "0.08590227"
     },
     {
      "Time": "1939",
      "Anomaly (deg C)": "-0.040797167",
      "Lower confidence limit (2.5%)": "-0.14670466",
      "Upper confidence limit (97,5%)": "0.065110326"
     },
     {
      "Time": "1940",
      "Anomaly (deg C)": "0.07593584",
      "Lower confidence limit (2.5%)": "-0.04194966",
      "Upper confidence limit (97,5%)": "0.19382134"
     },
     {
      "Time": "1941",
      "Anomaly (deg C)": "0.038129337",
      "Lower confidence limit (2.5%)": "-0.16225387",
      "Upper confidence limit (97,5%)": "0.23851255"
     },
     {
      "Time": "1942",
      "Anomaly (deg C)": "0.0014060909",
      "Lower confidence limit (2.5%)": "-0.1952124",
      "Upper confidence limit (97,5%)": "0.19802457"
     },
     {
      "Time": "1943",
      "Anomaly (deg C)": "0.0064140745",
      "Lower confidence limit (2.5%)": "-0.19959097",
      "Upper confidence limit (97,5%)": "0.21241911"
     },
     {
      "Time": "1944",
      "Anomaly (deg C)": "0.14410514",
      "Lower confidence limit (2.5%)": "-0.054494828",
      "Upper confidence limit (97,5%)": "0.3427051"
     },
     {
      "Time": "1945",
      "Anomaly (deg C)": "0.043088365",
      "Lower confidence limit (2.5%)": "-0.15728289",
      "Upper confidence limit (97,5%)": "0.24345961"
     },
     {
      "Time": "1946",
      "Anomaly (deg C)": "-0.1188128",
      "Lower confidence limit (2.5%)": "-0.2659574",
      "Upper confidence limit (97,5%)": "0.028331792"
     },
     {
      "Time": "1947",
      "Anomaly (deg C)": "-0.091205545",
      "Lower confidence limit (2.5%)": "-0.23179041",
      "Upper confidence limit (97,5%)": "0.04937931"
     },
     {
      "Time": "1948",
      "Anomaly (deg C)": "-0.12466127",
      "Lower confidence limit (2.5%)": "-0.25913337",
      "Upper confidence limit (97,5%)": "0.009810844"
     },
     {
      "Time": "1949",
      "Anomaly (deg C)": "-0.14380224",
      "Lower confidence limit (2.5%)": "-0.2540775",
      "Upper confidence limit (97,5%)": "-0.033526987"
     },
     {
      "Time": "1950",
      "Anomaly (deg C)": "-0.22662179",
      "Lower confidence limit (2.5%)": "-0.33265698",
      "Upper confidence limit (97,5%)": "-0.12058662"
     },
     {
      "Time": "1951",
      "Anomaly (deg C)": "-0.06115397",
      "Lower confidence limit (2.5%)": "-0.15035024",
      "Upper confidence limit (97,5%)": "0.028042298"
     },
     {
      "Time": "1952",
      "Anomaly (deg C)": "0.015354565",
      "Lower confidence limit (2.5%)": "-0.08293597",
      "Upper confidence limit (97,5%)": "0.11364509"
     },
     {
      "Time": "1953",
      "Anomaly (deg C)": "0.07763074",
      "Lower confidence limit (2.5%)": "-0.020529618",
      "Upper confidence limit (97,5%)": "0.1757911"
     },
     {
      "Time": "1954",
      "Anomaly (deg C)": "-0.11675021",
      "Lower confidence limit (2.5%)": "-0.20850271",
      "Upper confidence limit (97,5%)": "-0.024997713"
     },
     {
      "Time": "1955",
      "Anomaly (deg C)": "-0.19730993",
      "Lower confidence limit (2.5%)": "-0.28442997",
      "Upper confidence limit (97,5%)": "-0.1101899"
     },
     {
      "Time": "1956",
      "Anomaly (deg C)": "-0.2631656",
      "Lower confidence limit (2.5%)": "-0.33912563",
      "Upper confidence limit (97,5%)": "-0.18720557"
     },
     {
      "Time": "1957",
      "Anomaly (deg C)": "-0.035334926",
      "Lower confidence limit (2.5%)": "-0.10056862",
      "Upper confidence limit (97,5%)": "0.029898768"
     },
     {
      "Time": "1958",
      "Anomaly (deg C)": "-0.017632553",
      "Lower confidence limit (2.5%)": "-0.083074555",
      "Upper confidence limit (97,5%)": "0.04780945"
     },
     {
      "Time": "1959",
      "Anomaly (deg C)": "-0.048004825",
      "Lower confidence limit (2.5%)": "-0.11036375",
      "Upper confidence limit (97,5%)": "0.0143540995"
     },
     {
      "Time": "1960",
      "Anomaly (deg C)": "-0.115487024",
      "Lower confidence limit (2.5%)": "-0.17416587",
      "Upper confidence limit (97,5%)": "-0.056808177"
     },
     {
      "Time": "1961",
      "Anomaly (deg C)": "-0.019997388",
      "Lower confidence limit (2.5%)": "-0.07078052",
      "Upper confidence limit (97,5%)": "0.030785747"
     },
     {
      "Time": "1962",
      "Anomaly (deg C)": "-0.06405444",
      "Lower confidence limit (2.5%)": "-0.11731443",
      "Upper confidence limit (97,5%)": "-0.010794453"
     },
     {
      "Time": "1963",
      "Anomaly (deg C)": "-0.03680589",
      "Lower confidence limit (2.5%)": "-0.09057008",
      "Upper confidence limit (97,5%)": "0.016958294"
     },
     {
      "Time": "1964",
      "Anomaly (deg C)": "-0.30586675",
      "Lower confidence limit (2.5%)": "-0.34949213",
      "Upper confidence limit (97,5%)": "-0.26224136"
     },
     {
      "Time": "1965",
      "Anomaly (deg C)": "-0.2043879",
      "Lower confidence limit (2.5%)": "-0.25357357",
      "Upper confidence limit (97,5%)": "-0.15520222"
     },
     {
      "Time": "1966",
      "Anomaly (deg C)": "-0.14888458",
      "Lower confidence limit (2.5%)": "-0.19839221",
      "Upper confidence limit (97,5%)": "-0.09937696"
     },
     {
      "Time": "1967",
      "Anomaly (deg C)": "-0.11751631",
      "Lower confidence limit (2.5%)": "-0.16062479",
      "Upper confidence limit (97,5%)": "-0.07440783"
     },
     {
      "Time": "1968",
      "Anomaly (deg C)": "-0.1686323",
      "Lower confidence limit (2.5%)": "-0.21325313",
      "Upper confidence limit (97,5%)": "-0.124011464"
     },
     {
      "Time": "1969",
      "Anomaly (deg C)": "-0.031366713",
      "Lower confidence limit (2.5%)": "-0.07186544",
      "Upper confidence limit (97,5%)": "0.009132013"
     },
     {
      "Time": "1970",
      "Anomaly (deg C)": "-0.08510657",
      "Lower confidence limit (2.5%)": "-0.12608096",
      "Upper confidence limit (97,5%)": "-0.04413217"
     },
     {
      "Time": "1971",
      "Anomaly (deg C)": "-0.20593274",
      "Lower confidence limit (2.5%)": "-0.24450706",
      "Upper confidence limit (97,5%)": "-0.16735843"
     },
     {
      "Time": "1972",
      "Anomaly (deg C)": "-0.0938271",
      "Lower confidence limit (2.5%)": "-0.13171694",
      "Upper confidence limit (97,5%)": "-0.05593726"
     },
     {
      "Time": "1973",
      "Anomaly (deg C)": "0.04993336",
      "Lower confidence limit (2.5%)": "0.013468528",
      "Upper confidence limit (97,5%)": "0.086398184"
     },
     {
      "Time": "1974",
      "Anomaly (deg C)": "-0.17253734",
      "Lower confidence limit (2.5%)": "-0.21022376",
      "Upper confidence limit (97,5%)": "-0.1348509"
     },
     {
      "Time": "1975",
      "Anomaly (deg C)": "-0.11075424",
      "Lower confidence limit (2.5%)": "-0.15130512",
      "Upper confidence limit (97,5%)": "-0.07020335"
     },
     {
      "Time": "1976",
      "Anomaly (deg C)": "-0.21586166",
      "Lower confidence limit (2.5%)": "-0.25588378",
      "Upper confidence limit (97,5%)": "-0.17583954"
     },
     {
      "Time": "1977",
      "Anomaly (deg C)": "0.10308852",
      "Lower confidence limit (2.5%)": "0.060056705",
      "Upper confidence limit (97,5%)": "0.14612034"
     },
     {
      "Time": "1978",
      "Anomaly (deg C)": "0.0052557723",
      "Lower confidence limit (2.5%)": "-0.034576867",
      "Upper confidence limit (97,5%)": "0.04508841"
     },
     {
      "Time": "1979",
      "Anomaly (deg C)": "0.09085813",
      "Lower confidence limit (2.5%)": "0.062358618",
      "Upper confidence limit (97,5%)": "0.119357646"
     },
     {
      "Time": "1980",
      "Anomaly (deg C)": "0.19607207",
      "Lower confidence limit (2.5%)": "0.162804",
      "Upper confidence limit (97,5%)": "0.22934014"
     },
     {
      "Time": "1981",
      "Anomaly (deg C)": "0.25001204",
      "Lower confidence limit (2.5%)": "0.21939126",
      "Upper confidence limit (97,5%)": "0.28063282"
     },
     {
      "Time": "1982",
      "Anomaly (deg C)": "0.034263328",
      "Lower confidence limit (2.5%)": "-0.005104665",
      "Upper confidence limit (97,5%)": "0.07363132"
     },
     {
      "Time": "1983",
      "Anomaly (deg C)": "0.22383861",
      "Lower confidence limit (2.5%)": "0.18807402",
      "Upper confidence limit (97,5%)": "0.2596032"
     },
     {
      "Time": "1984",
      "Anomaly (deg C)": "0.04800471",
      "Lower confidence limit (2.5%)": "0.011560736",
      "Upper confidence limit (97,5%)": "0.08444869"
     },
     {
      "Time": "1985",
      "Anomaly (deg C)": "0.04972978",
      "Lower confidence limit (2.5%)": "0.015663471",
      "Upper confidence limit (97,5%)": "0.08379609"
     },
     {
      "Time": "1986",
      "Anomaly (deg C)": "0.09568697",
      "Lower confidence limit (2.5%)": "0.064408",
      "Upper confidence limit (97,5%)": "0.12696595"
     },
     {
      "Time": "1987",
      "Anomaly (deg C)": "0.2430264",
      "Lower confidence limit (2.5%)": "0.21218552",
      "Upper confidence limit (97,5%)": "0.27386728"
     },
     {
      "Time": "1988",
      "Anomaly (deg C)": "0.28215173",
      "Lower confidence limit (2.5%)": "0.2470353",
      "Upper confidence limit (97,5%)": "0.31726816"
     },
     {
      "Time": "1989",
      "Anomaly (deg C)": "0.17925027",
      "Lower confidence limit (2.5%)": "0.14449838",
      "Upper confidence limit (97,5%)": "0.21400215"
     },
     {
      "Time": "1990",
      "Anomaly (deg C)": "0.36056247",
      "Lower confidence limit (2.5%)": "0.32455227",
      "Upper confidence limit (97,5%)": "0.39657268"
     },
     {
      "Time": "1991",
      "Anomaly (deg C)": "0.33889654",
      "Lower confidence limit (2.5%)": "0.30403617",
      "Upper confidence limit (97,5%)": "0.3737569"
     },
     {
      "Time": "1992",
      "Anomaly (deg C)": "0.124896795",
      "Lower confidence limit (2.5%)": "0.09088206",
      "Upper confidence limit (97,5%)": "0.15891153"
     },
     {
      "Time": "1993",
      "Anomaly (deg C)": "0.16565846",
      "Lower confidence limit (2.5%)": "0.12817313",
      "Upper confidence limit (97,5%)": "0.2031438"
     },
     {
      "Time": "1994",
      "Anomaly (deg C)": "0.23354977",
      "Lower confidence limit (2.5%)": "0.19841294",
      "Upper confidence limit (97,5%)": "0.2686866"
     },
     {
      "Time": "1995",
      "Anomaly (deg C)": "0.37686616",
      "Lower confidence limit (2.5%)": "0.34365577",
      "Upper confidence limit (97,5%)": "0.41007656"
     },
     {
      "Time": "1996",
      "Anomaly (deg C)": "0.2766894",
      "Lower confidence limit (2.5%)": "0.24318004",
      "Upper confidence limit (97,5%)": "0.31019878"
     },
     {
      "Time": "1997",
      "Anomaly (deg C)": "0.4223085",
      "Lower confidence limit (2.5%)": "0.39009082",
      "Upper confidence limit (97,5%)": "0.4545262"
     },
     {
      "Time": "1998",
      "Anomaly (deg C)": "0.57731646",
      "Lower confidence limit (2.5%)": "0.54304415",
      "Upper confidence limit (97,5%)": "0.6115888"
     },
     {
      "Time": "1999",
      "Anomaly (deg C)": "0.32448497",
      "Lower confidence limit (2.5%)": "0.29283476",
      "Upper confidence limit (97,5%)": "0.35613516"
     },
     {
      "Time": "2000",
      "Anomaly (deg C)": "0.3310848",
      "Lower confidence limit (2.5%)": "0.29822788",
      "Upper confidence limit (97,5%)": "0.36394167"
     },
     {
      "Time": "2001",
      "Anomaly (deg C)": "0.48928034",
      "Lower confidence limit (2.5%)": "0.4580683",
      "Upper confidence limit (97,5%)": "0.5204924"
     },
     {
      "Time": "2002",
      "Anomaly (deg C)": "0.5434665",
      "Lower confidence limit (2.5%)": "0.51278186",
      "Upper confidence limit (97,5%)": "0.57415116"
     },
     {
      "Time": "2003",
      "Anomaly (deg C)": "0.5441702",
      "Lower confidence limit (2.5%)": "0.5112426",
      "Upper confidence limit (97,5%)": "0.5770977"
     },
     {
      "Time": "2004",
      "Anomaly (deg C)": "0.46737072",
      "Lower confidence limit (2.5%)": "0.43433833",
      "Upper confidence limit (97,5%)": "0.5004031"
     },
     {
      "Time": "2005",
      "Anomaly (deg C)": "0.60686255",
      "Lower confidence limit (2.5%)": "0.5757053",
      "Upper confidence limit (97,5%)": "0.6380198"
     },
     {
      "Time": "2006",
      "Anomaly (deg C)": "0.5725527",
      "Lower confidence limit (2.5%)": "0.541973",
      "Upper confidence limit (97,5%)": "0.60313237"
     },
     {
      "Time": "2007",
      "Anomaly (deg C)": "0.5917013",
      "Lower confidence limit (2.5%)": "0.56135315",
      "Upper confidence limit (97,5%)": "0.6220495"
     },
     {
      "Time": "2008",
      "Anomaly (deg C)": "0.46564984",
      "Lower confidence limit (2.5%)": "0.43265733",
      "Upper confidence limit (97,5%)": "0.49864236"
     },
     {
      "Time": "2009",
      "Anomaly (deg C)": "0.5967817",
      "Lower confidence limit (2.5%)": "0.56525564",
      "Upper confidence limit (97,5%)": "0.6283077"
     },
     {
      "Time": "2010",
      "Anomaly (deg C)": "0.68037146",
      "Lower confidence limit (2.5%)": "0.649076",
      "Upper confidence limit (97,5%)": "0.7116669"
     },
     {
      "Time": "2011",
      "Anomaly (deg C)": "0.53769773",
      "Lower confidence limit (2.5%)": "0.5060012",
      "Upper confidence limit (97,5%)": "0.5693943"
     },
     {
      "Time": "2012",
      "Anomaly (deg C)": "0.5776071",
      "Lower confidence limit (2.5%)": "0.5448553",
      "Upper confidence limit (97,5%)": "0.6103589"
     },
     {
      "Time": "2013",
      "Anomaly (deg C)": "0.6235754",
      "Lower confidence limit (2.5%)": "0.5884838",
      "Upper confidence limit (97,5%)": "0.6586669"
     },
     {
      "Time": "2014",
      "Anomaly (deg C)": "0.67287165",
      "Lower confidence limit (2.5%)": "0.63890487",
      "Upper confidence limit (97,5%)": "0.7068384"
     },
     {
      "Time": "2015",
      "Anomaly (deg C)": "0.82511437",
      "Lower confidence limit (2.5%)": "0.79128706",
      "Upper confidence limit (97,5%)": "0.8589417"
     },
     {
      "Time": "2016",
      "Anomaly (deg C)": "0.93292713",
      "Lower confidence limit (2.5%)": "0.90176356",
      "Upper confidence limit (97,5%)": "0.96409065"
     },
     {
      "Time": "2017",
      "Anomaly (deg C)": "0.84517425",
      "Lower confidence limit (2.5%)": "0.81477475",
      "Upper confidence limit (97,5%)": "0.87557375"
     },
     {
      "Time": "2018",
      "Anomaly (deg C)": "0.762654",
      "Lower confidence limit (2.5%)": "0.731052",
      "Upper confidence limit (97,5%)": "0.79425603"
     },
     {
      "Time": "2019",
      "Anomaly (deg C)": "0.8910726",
      "Lower confidence limit (2.5%)": "0.85678726",
      "Upper confidence limit (97,5%)": "0.92535794"
     },
     {
      "Time": "2020",
      "Anomaly (deg C)": "0.9227938",
      "Lower confidence limit (2.5%)": "0.8882121",
      "Upper confidence limit (97,5%)": "0.9573755"
     },
     {
      "Time": "2021",
      "Anomaly (deg C)": "0.7618559",
      "Lower confidence limit (2.5%)": "0.72544336",
      "Upper confidence limit (97,5%)": "0.79826844"
     },
     {
      "Time": "2022",
      "Anomaly (deg C)": "0.80128413",
      "Lower confidence limit (2.5%)": "0.7652511",
      "Upper confidence limit (97,5%)": "0.8373171"
     },
     {
      "Time": "2023",
      "Anomaly (deg C)": "0.7755153",
      "Lower confidence limit (2.5%)": "0.52228117",
      "Upper confidence limit (97,5%)": "1.0287495"
     }
    ],
    "HadCRUT.5.0.1.0.analysis.summar":[
     {
      "Time,Anomaly (deg C),Lower confidence limit (2.5%),Upper confidence limit (97.5%)": "1850,-0.41765878,-0.589203,-0.24611452"
     },
     {
      "Time,Anomaly (deg C),Lower confidence limit (2.5%),Upper confidence limit (97.5%)": "1851,-0.2333498,-0.41186792,-0.054831687"
     },
     {
      "Time,Anomaly (deg C),Lower confidence limit (2.5%),Upper confidence limit (97.5%)": "1852,-0.22939907,-0.40938243,-0.04941572"
     },
     {
      "Time,Anomaly (deg C),Lower confidence limit (2.5%),Upper confidence limit (97.5%)": "1853,-0.27035445,-0.43000934,-0.110699534"
     },
     {
      "Time,Anomaly (deg C),Lower confidence limit (2.5%),Upper confidence limit (97.5%)": "1854,-0.29163003,-0.43282393,-0.15043613"
     },
     {
      "Time,Anomaly (deg C),Lower confidence limit (2.5%),Upper confidence limit (97.5%)": "1855,-0.2969512,-0.43935776,-0.15454465"
     },
     {
      "Time,Anomaly (deg C),Lower confidence limit (2.5%),Upper confidence limit (97.5%)": "1856,-0.32035372,-0.46809322,-0.1726142"
     },
     {
      "Time,Anomaly (deg C),Lower confidence limit (2.5%),Upper confidence limit (97.5%)": "1857,-0.46723005,-0.61632216,-0.31813794"
     },
     {
      "Time,Anomaly (deg C),Lower confidence limit (2.5%),Upper confidence limit (97.5%)": "1858,-0.3887657,-0.53688604,-0.24064532"
     },
     {
      "Time,Anomaly (deg C),Lower confidence limit (2.5%),Upper confidence limit (97.5%)": "1859,-0.28119546,-0.42384982,-0.13854107"
     },
     {
      "Time,Anomaly (deg C),Lower confidence limit (2.5%),Upper confidence limit (97.5%)": "1860,-0.39016518,-0.5389766,-0.24135375"
     },
     {
      "Time,Anomaly (deg C),Lower confidence limit (2.5%),Upper confidence limit (97.5%)": "1861,-0.42927712,-0.5972301,-0.26132414"
     },
     {
      "Time,Anomaly (deg C),Lower confidence limit (2.5%),Upper confidence limit (97.5%)": "1862,-0.53639776,-0.7037096,-0.36908585"
     },
     {
      "Time,Anomaly (deg C),Lower confidence limit (2.5%),Upper confidence limit (97.5%)": "1863,-0.3443432,-0.5341645,-0.1545219"
     },
     {
      "Time,Anomaly (deg C),Lower confidence limit (2.5%),Upper confidence limit (97.5%)": "1864,-0.4654367,-0.6480974,-0.282776"
     },
     {
      "Time,Anomaly (deg C),Lower confidence limit (2.5%),Upper confidence limit (97.5%)": "1865,-0.33258784,-0.5246526,-0.14052312"
     },
     {
      "Time,Anomaly (deg C),Lower confidence limit (2.5%),Upper confidence limit (97.5%)": "1866,-0.34126064,-0.52183825,-0.16068307"
     },
     {
      "Time,Anomaly (deg C),Lower confidence limit (2.5%),Upper confidence limit (97.5%)": "1867,-0.35696334,-0.55306214,-0.16086453"
     },
     {
      "Time,Anomaly (deg C),Lower confidence limit (2.5%),Upper confidence limit (97.5%)": "1868,-0.35196072,-0.52965826,-0.17426313"
     },
     {
      "Time,Anomaly (deg C),Lower confidence limit (2.5%),Upper confidence limit (97.5%)": "1869,-0.31657043,-0.47642276,-0.15671812"
     },
     {
      "Time,Anomaly (deg C),Lower confidence limit (2.5%),Upper confidence limit (97.5%)": "1870,-0.32789087,-0.46867347,-0.18710826"
     },
     {
      "Time,Anomaly (deg C),Lower confidence limit (2.5%),Upper confidence limit (97.5%)": "1871,-0.3685807,-0.5141493,-0.22301209"
     },
     {
      "Time,Anomaly (deg C),Lower confidence limit (2.5%),Upper confidence limit (97.5%)": "1872,-0.32804197,-0.4630833,-0.19300064"
     },
     {
      "Time,Anomaly (deg C),Lower confidence limit (2.5%),Upper confidence limit (97.5%)": "1873,-0.34133235,-0.4725396,-0.21012507"
     },
     {
      "Time,Anomaly (deg C),Lower confidence limit (2.5%),Upper confidence limit (97.5%)": "1874,-0.3732512,-0.5071426,-0.2393598"
     },
     {
      "Time,Anomaly (deg C),Lower confidence limit (2.5%),Upper confidence limit (97.5%)": "1875,-0.37562594,-0.514041,-0.23721085"
     },
     {
      "Time,Anomaly (deg C),Lower confidence limit (2.5%),Upper confidence limit (97.5%)": "1876,-0.42410994,-0.56287116,-0.28534868"
     },
     {
      "Time,Anomaly (deg C),Lower confidence limit (2.5%),Upper confidence limit (97.5%)": "1877,-0.101108834,-0.22982001,0.027602348"
     },
     {
      "Time,Anomaly (deg C),Lower confidence limit (2.5%),Upper confidence limit (97.5%)": "1878,-0.011315193,-0.13121258,0.10858219"
     },
     {
      "Time,Anomaly (deg C),Lower confidence limit (2.5%),Upper confidence limit (97.5%)": "1879,-0.30363432,-0.43406433,-0.1732043"
     },
     {
      "Time,Anomaly (deg C),Lower confidence limit (2.5%),Upper confidence limit (97.5%)": "1880,-0.31583208,-0.44015095,-0.19151321"
     },
     {
      "Time,Anomaly (deg C),Lower confidence limit (2.5%),Upper confidence limit (97.5%)": "1881,-0.23224552,-0.35793498,-0.10655605"
     },
     {
      "Time,Anomaly (deg C),Lower confidence limit (2.5%),Upper confidence limit (97.5%)": "1882,-0.29553008,-0.4201501,-0.17091006"
     },
     {
      "Time,Anomaly (deg C),Lower confidence limit (2.5%),Upper confidence limit (97.5%)": "1883,-0.3464744,-0.4608177,-0.23213111"
     },
     {
      "Time,Anomaly (deg C),Lower confidence limit (2.5%),Upper confidence limit (97.5%)": "1884,-0.49232006,-0.6026686,-0.38197154"
     },
     {
      "Time,Anomaly (deg C),Lower confidence limit (2.5%),Upper confidence limit (97.5%)": "1885,-0.47112358,-0.5830682,-0.35917896"
     },
     {
      "Time,Anomaly (deg C),Lower confidence limit (2.5%),Upper confidence limit (97.5%)": "1886,-0.42090362,-0.5225382,-0.31926903"
     },
     {
      "Time,Anomaly (deg C),Lower confidence limit (2.5%),Upper confidence limit (97.5%)": "1887,-0.49878576,-0.61655986,-0.3810117"
     },
     {
      "Time,Anomaly (deg C),Lower confidence limit (2.5%),Upper confidence limit (97.5%)": "1888,-0.37937889,-0.49332377,-0.265434"
     },
     {
      "Time,Anomaly (deg C),Lower confidence limit (2.5%),Upper confidence limit (97.5%)": "1889,-0.24989556,-0.37222093,-0.12757017"
     },
     {
      "Time,Anomaly (deg C),Lower confidence limit (2.5%),Upper confidence limit (97.5%)": "1890,-0.50685817,-0.6324095,-0.3813068"
     },
     {
      "Time,Anomaly (deg C),Lower confidence limit (2.5%),Upper confidence limit (97.5%)": "1891,-0.40131494,-0.5373699,-0.26525995"
     },
     {
      "Time,Anomaly (deg C),Lower confidence limit (2.5%),Upper confidence limit (97.5%)": "1892,-0.5075585,-0.64432853,-0.3707885"
     },
     {
      "Time,Anomaly (deg C),Lower confidence limit (2.5%),Upper confidence limit (97.5%)": "1893,-0.49461925,-0.6315314,-0.35770702"
     },
     {
      "Time,Anomaly (deg C),Lower confidence limit (2.5%),Upper confidence limit (97.5%)": "1894,-0.48376393,-0.6255681,-0.34195974"
     },
     {
      "Time,Anomaly (deg C),Lower confidence limit (2.5%),Upper confidence limit (97.5%)": "1895,-0.4487516,-0.58202064,-0.3154826"
     },
     {
      "Time,Anomaly (deg C),Lower confidence limit (2.5%),Upper confidence limit (97.5%)": "1896,-0.28400728,-0.4174015,-0.15061308"
     },
     {
      "Time,Anomaly (deg C),Lower confidence limit (2.5%),Upper confidence limit (97.5%)": "1897,-0.25980017,-0.39852425,-0.12107607"
     },
     {
      "Time,Anomaly (deg C),Lower confidence limit (2.5%),Upper confidence limit (97.5%)": "1898,-0.48579213,-0.6176492,-0.35393503"
     },
     {
      "Time,Anomaly (deg C),Lower confidence limit (2.5%),Upper confidence limit (97.5%)": "1899,-0.35543364,-0.48639694,-0.22447036"
     },
     {
      "Time,Anomaly (deg C),Lower confidence limit (2.5%),Upper confidence limit (97.5%)": "1900,-0.23447904,-0.3669676,-0.10199049"
     },
     {
      "Time,Anomaly (deg C),Lower confidence limit (2.5%),Upper confidence limit (97.5%)": "1901,-0.29342857,-0.42967388,-0.15718324"
     },
     {
      "Time,Anomaly (deg C),Lower confidence limit (2.5%),Upper confidence limit (97.5%)": "1902,-0.43898427,-0.5754281,-0.30254042"
     },
     {
      "Time,Anomaly (deg C),Lower confidence limit (2.5%),Upper confidence limit (97.5%)": "1903,-0.5333264,-0.66081935,-0.40583345"
     },
     {
      "Time,Anomaly (deg C),Lower confidence limit (2.5%),Upper confidence limit (97.5%)": "1904,-0.5975614,-0.7288325,-0.46629035"
     },
     {
      "Time,Anomaly (deg C),Lower confidence limit (2.5%),Upper confidence limit (97.5%)": "1905,-0.40775132,-0.5350291,-0.28047356"
     },
     {
      "Time,Anomaly (deg C),Lower confidence limit (2.5%),Upper confidence limit (97.5%)": "1906,-0.3191393,-0.45052385,-0.18775477"
     },
     {
      "Time,Anomaly (deg C),Lower confidence limit (2.5%),Upper confidence limit (97.5%)": "1907,-0.5041577,-0.6262818,-0.38203365"
     },
     {
      "Time,Anomaly (deg C),Lower confidence limit (2.5%),Upper confidence limit (97.5%)": "1908,-0.5138707,-0.63748026,-0.3902612"
     },
     {
      "Time,Anomaly (deg C),Lower confidence limit (2.5%),Upper confidence limit (97.5%)": "1909,-0.5357649,-0.6526296,-0.41890016"
     },
     {
      "Time,Anomaly (deg C),Lower confidence limit (2.5%),Upper confidence limit (97.5%)": "1910,-0.5310242,-0.6556868,-0.40636164"
     },
     {
      "Time,Anomaly (deg C),Lower confidence limit (2.5%),Upper confidence limit (97.5%)": "1911,-0.5392051,-0.66223973,-0.4161705"
     },
     {
      "Time,Anomaly (deg C),Lower confidence limit (2.5%),Upper confidence limit (97.5%)": "1912,-0.47567302,-0.5893311,-0.36201498"
     },
     {
      "Time,Anomaly (deg C),Lower confidence limit (2.5%),Upper confidence limit (97.5%)": "1913,-0.46715254,-0.5893755,-0.34492958"
     },
     {
      "Time,Anomaly (deg C),Lower confidence limit (2.5%),Upper confidence limit (97.5%)": "1914,-0.2625924,-0.38276345,-0.1424214"
     },
     {
      "Time,Anomaly (deg C),Lower confidence limit (2.5%),Upper confidence limit (97.5%)": "1915,-0.19184391,-0.32196194,-0.06172589"
     },
     {
      "Time,Anomaly (deg C),Lower confidence limit (2.5%),Upper confidence limit (97.5%)": "1916,-0.42020997,-0.5588941,-0.28152588"
     },
     {
      "Time,Anomaly (deg C),Lower confidence limit (2.5%),Upper confidence limit (97.5%)": "1917,-0.54301953,-0.6921192,-0.3939199"
     },
     {
      "Time,Anomaly (deg C),Lower confidence limit (2.5%),Upper confidence limit (97.5%)": "1918,-0.42458433,-0.58198184,-0.26718682"
     },
     {
      "Time,Anomaly (deg C),Lower confidence limit (2.5%),Upper confidence limit (97.5%)": "1919,-0.32551822,-0.48145813,-0.1695783"
     },
     {
      "Time,Anomaly (deg C),Lower confidence limit (2.5%),Upper confidence limit (97.5%)": "1920,-0.2985808,-0.44860035,-0.14856121"
     },
     {
      "Time,Anomaly (deg C),Lower confidence limit (2.5%),Upper confidence limit (97.5%)": "1921,-0.24067703,-0.38175339,-0.09960067"
     },
     {
      "Time,Anomaly (deg C),Lower confidence limit (2.5%),Upper confidence limit (97.5%)": "1922,-0.33922812,-0.46610323,-0.21235302"
     },
     {
      "Time,Anomaly (deg C),Lower confidence limit (2.5%),Upper confidence limit (97.5%)": "1923,-0.31793055,-0.444173,-0.1916881"
     },
     {
      "Time,Anomaly (deg C),Lower confidence limit (2.5%),Upper confidence limit (97.5%)": "1924,-0.3120622,-0.4388317,-0.18529275"
     },
     {
      "Time,Anomaly (deg C),Lower confidence limit (2.5%),Upper confidence limit (97.5%)": "1925,-0.28242525,-0.4147755,-0.15007503"
     },
     {
      "Time,Anomaly (deg C),Lower confidence limit (2.5%),Upper confidence limit (97.5%)": "1926,-0.12283547,-0.25264767,0.006976739"
     },
     {
      "Time,Anomaly (deg C),Lower confidence limit (2.5%),Upper confidence limit (97.5%)": "1927,-0.22940508,-0.35135695,-0.10745319"
     },
     {
      "Time,Anomaly (deg C),Lower confidence limit (2.5%),Upper confidence limit (97.5%)": "1928,-0.20676155,-0.33881804,-0.074705064"
     },
     {
      "Time,Anomaly (deg C),Lower confidence limit (2.5%),Upper confidence limit (97.5%)": "1929,-0.39275664,-0.52656746,-0.25894582"
     },
     {
      "Time,Anomaly (deg C),Lower confidence limit (2.5%),Upper confidence limit (97.5%)": "1930,-0.1768054,-0.29041144,-0.06319936"
     },
     {
      "Time,Anomaly (deg C),Lower confidence limit (2.5%),Upper confidence limit (97.5%)": "1931,-0.10339768,-0.2126916,0.0058962475"
     },
     {
      "Time,Anomaly (deg C),Lower confidence limit (2.5%),Upper confidence limit (97.5%)": "1932,-0.14546166,-0.25195515,-0.0389682"
     },
     {
      "Time,Anomaly (deg C),Lower confidence limit (2.5%),Upper confidence limit (97.5%)": "1933,-0.32234442,-0.4271004,-0.21758842"
     },
     {
      "Time,Anomaly (deg C),Lower confidence limit (2.5%),Upper confidence limit (97.5%)": "1934,-0.17433685,-0.27400395,-0.07466974"
     },
     {
      "Time,Anomaly (deg C),Lower confidence limit (2.5%),Upper confidence limit (97.5%)": "1935,-0.20605922,-0.30349734,-0.10862111"
     },
     {
      "Time,Anomaly (deg C),Lower confidence limit (2.5%),Upper confidence limit (97.5%)": "1936,-0.16952093,-0.26351926,-0.07552261"
     },
     {
      "Time,Anomaly (deg C),Lower confidence limit (2.5%),Upper confidence limit (97.5%)": "1937,-0.01919893,-0.11975875,0.08136089"
     },
     {
      "Time,Anomaly (deg C),Lower confidence limit (2.5%),Upper confidence limit (97.5%)": "1938,-0.012200732,-0.11030374,0.08590227"
     },
     {
      "Time,Anomaly (deg C),Lower confidence limit (2.5%),Upper confidence limit (97.5%)": "1939,-0.040797167,-0.14670466,0.065110326"
     },
     {
      "Time,Anomaly (deg C),Lower confidence limit (2.5%),Upper confidence limit (97.5%)": "1940,0.07593584,-0.04194966,0.19382134"
     },
     {
      "Time,Anomaly (deg C),Lower confidence limit (2.5%),Upper confidence limit (97.5%)": "1941,0.038129337,-0.16225387,0.23851255"
     },
     {
      "Time,Anomaly (deg C),Lower confidence limit (2.5%),Upper confidence limit (97.5%)": "1942,0.0014060909,-0.1952124,0.19802457"
     },
     {
      "Time,Anomaly (deg C),Lower confidence limit (2.5%),Upper confidence limit (97.5%)": "1943,0.0064140745,-0.19959097,0.21241911"
     },
     {
      "Time,Anomaly (deg C),Lower confidence limit (2.5%),Upper confidence limit (97.5%)": "1944,0.14410514,-0.054494828,0.3427051"
     },
     {
      "Time,Anomaly (deg C),Lower confidence limit (2.5%),Upper confidence limit (97.5%)": "1945,0.043088365,-0.15728289,0.24345961"
     },
     {
      "Time,Anomaly (deg C),Lower confidence limit (2.5%),Upper confidence limit (97.5%)": "1946,-0.1188128,-0.2659574,0.028331792"
     },
     {
      "Time,Anomaly (deg C),Lower confidence limit (2.5%),Upper confidence limit (97.5%)": "1947,-0.091205545,-0.23179041,0.04937931"
     },
     {
      "Time,Anomaly (deg C),Lower confidence limit (2.5%),Upper confidence limit (97.5%)": "1948,-0.12466127,-0.25913337,0.009810844"
     },
     {
      "Time,Anomaly (deg C),Lower confidence limit (2.5%),Upper confidence limit (97.5%)": "1949,-0.14380224,-0.2540775,-0.033526987"
     },
     {
      "Time,Anomaly (deg C),Lower confidence limit (2.5%),Upper confidence limit (97.5%)": "1950,-0.22662179,-0.33265698,-0.12058662"
     },
     {
      "Time,Anomaly (deg C),Lower confidence limit (2.5%),Upper confidence limit (97.5%)": "1951,-0.06115397,-0.15035024,0.028042298"
     },
     {
      "Time,Anomaly (deg C),Lower confidence limit (2.5%),Upper confidence limit (97.5%)": "1952,0.015354565,-0.08293597,0.11364509"
     },
     {
      "Time,Anomaly (deg C),Lower confidence limit (2.5%),Upper confidence limit (97.5%)": "1953,0.07763074,-0.020529618,0.1757911"
     },
     {
      "Time,Anomaly (deg C),Lower confidence limit (2.5%),Upper confidence limit (97.5%)": "1954,-0.11675021,-0.20850271,-0.024997713"
     },
     {
      "Time,Anomaly (deg C),Lower confidence limit (2.5%),Upper confidence limit (97.5%)": "1955,-0.19730993,-0.28442997,-0.1101899"
     },
     {
      "Time,Anomaly (deg C),Lower confidence limit (2.5%),Upper confidence limit (97.5%)": "1956,-0.2631656,-0.33912563,-0.18720557"
     },
     {
      "Time,Anomaly (deg C),Lower confidence limit (2.5%),Upper confidence limit (97.5%)": "1957,-0.035334926,-0.10056862,0.029898768"
     },
     {
      "Time,Anomaly (deg C),Lower confidence limit (2.5%),Upper confidence limit (97.5%)": "1958,-0.017632553,-0.083074555,0.04780945"
     },
     {
      "Time,Anomaly (deg C),Lower confidence limit (2.5%),Upper confidence limit (97.5%)": "1959,-0.048004825,-0.11036375,0.0143540995"
     },
     {
      "Time,Anomaly (deg C),Lower confidence limit (2.5%),Upper confidence limit (97.5%)": "1960,-0.115487024,-0.17416587,-0.056808177"
     },
     {
      "Time,Anomaly (deg C),Lower confidence limit (2.5%),Upper confidence limit (97.5%)": "1961,-0.019997388,-0.07078052,0.030785747"
     },
     {
      "Time,Anomaly (deg C),Lower confidence limit (2.5%),Upper confidence limit (97.5%)": "1962,-0.06405444,-0.11731443,-0.010794453"
     },
     {
      "Time,Anomaly (deg C),Lower confidence limit (2.5%),Upper confidence limit (97.5%)": "1963,-0.03680589,-0.09057008,0.016958294"
     },
     {
      "Time,Anomaly (deg C),Lower confidence limit (2.5%),Upper confidence limit (97.5%)": "1964,-0.30586675,-0.34949213,-0.26224136"
     },
     {
      "Time,Anomaly (deg C),Lower confidence limit (2.5%),Upper confidence limit (97.5%)": "1965,-0.2043879,-0.25357357,-0.15520222"
     },
     {
      "Time,Anomaly (deg C),Lower confidence limit (2.5%),Upper confidence limit (97.5%)": "1966,-0.14888458,-0.19839221,-0.09937696"
     },
     {
      "Time,Anomaly (deg C),Lower confidence limit (2.5%),Upper confidence limit (97.5%)": "1967,-0.11751631,-0.16062479,-0.07440783"
     },
     {
      "Time,Anomaly (deg C),Lower confidence limit (2.5%),Upper confidence limit (97.5%)": "1968,-0.1686323,-0.21325313,-0.124011464"
     },
     {
      "Time,Anomaly (deg C),Lower confidence limit (2.5%),Upper confidence limit (97.5%)": "1969,-0.031366713,-0.07186544,0.009132013"
     },
     {
      "Time,Anomaly (deg C),Lower confidence limit (2.5%),Upper confidence limit (97.5%)": "1970,-0.08510657,-0.12608096,-0.04413217"
     },
     {
      "Time,Anomaly (deg C),Lower confidence limit (2.5%),Upper confidence limit (97.5%)": "1971,-0.20593274,-0.24450706,-0.16735843"
     },
     {
      "Time,Anomaly (deg C),Lower confidence limit (2.5%),Upper confidence limit (97.5%)": "1972,-0.0938271,-0.13171694,-0.05593726"
     },
     {
      "Time,Anomaly (deg C),Lower confidence limit (2.5%),Upper confidence limit (97.5%)": "1973,0.04993336,0.013468528,0.086398184"
     },
     {
      "Time,Anomaly (deg C),Lower confidence limit (2.5%),Upper confidence limit (97.5%)": "1974,-0.17253734,-0.21022376,-0.1348509"
     },
     {
      "Time,Anomaly (deg C),Lower confidence limit (2.5%),Upper confidence limit (97.5%)": "1975,-0.11075424,-0.15130512,-0.07020335"
     },
     {
      "Time,Anomaly (deg C),Lower confidence limit (2.5%),Upper confidence limit (97.5%)": "1976,-0.21586166,-0.25588378,-0.17583954"
     },
     {
      "Time,Anomaly (deg C),Lower confidence limit (2.5%),Upper confidence limit (97.5%)": "1977,0.10308852,0.060056705,0.14612034"
     },
     {
      "Time,Anomaly (deg C),Lower confidence limit (2.5%),Upper confidence limit (97.5%)": "1978,0.0052557723,-0.034576867,0.04508841"
     },
     {
      "Time,Anomaly (deg C),Lower confidence limit (2.5%),Upper confidence limit (97.5%)": "1979,0.09085813,0.062358618,0.119357646"
     },
     {
      "Time,Anomaly (deg C),Lower confidence limit (2.5%),Upper confidence limit (97.5%)": "1980,0.19607207,0.162804,0.22934014"
     },
     {
      "Time,Anomaly (deg C),Lower confidence limit (2.5%),Upper confidence limit (97.5%)": "1981,0.25001204,0.21939126,0.28063282"
     },
     {
      "Time,Anomaly (deg C),Lower confidence limit (2.5%),Upper confidence limit (97.5%)": "1982,0.034263328,-0.005104665,0.07363132"
     },
     {
      "Time,Anomaly (deg C),Lower confidence limit (2.5%),Upper confidence limit (97.5%)": "1983,0.22383861,0.18807402,0.2596032"
     },
     {
      "Time,Anomaly (deg C),Lower confidence limit (2.5%),Upper confidence limit (97.5%)": "1984,0.04800471,0.011560736,0.08444869"
     },
     {
      "Time,Anomaly (deg C),Lower confidence limit (2.5%),Upper confidence limit (97.5%)": "1985,0.04972978,0.015663471,0.08379609"
     },
     {
      "Time,Anomaly (deg C),Lower confidence limit (2.5%),Upper confidence limit (97.5%)": "1986,0.09568697,0.064408,0.12696595"
     },
     {
      "Time,Anomaly (deg C),Lower confidence limit (2.5%),Upper confidence limit (97.5%)": "1987,0.2430264,0.21218552,0.27386728"
     },
     {
      "Time,Anomaly (deg C),Lower confidence limit (2.5%),Upper confidence limit (97.5%)": "1988,0.28215173,0.2470353,0.31726816"
     },
     {
      "Time,Anomaly (deg C),Lower confidence limit (2.5%),Upper confidence limit (97.5%)": "1989,0.17925027,0.14449838,0.21400215"
     },
     {
      "Time,Anomaly (deg C),Lower confidence limit (2.5%),Upper confidence limit (97.5%)": "1990,0.36056247,0.32455227,0.39657268"
     },
     {
      "Time,Anomaly (deg C),Lower confidence limit (2.5%),Upper confidence limit (97.5%)": "1991,0.33889654,0.30403617,0.3737569"
     },
     {
      "Time,Anomaly (deg C),Lower confidence limit (2.5%),Upper confidence limit (97.5%)": "1992,0.124896795,0.09088206,0.15891153"
     },
     {
      "Time,Anomaly (deg C),Lower confidence limit (2.5%),Upper confidence limit (97.5%)": "1993,0.16565846,0.12817313,0.2031438"
     },
     {
      "Time,Anomaly (deg C),Lower confidence limit (2.5%),Upper confidence limit (97.5%)": "1994,0.23354977,0.19841294,0.2686866"
     },
     {
      "Time,Anomaly (deg C),Lower confidence limit (2.5%),Upper confidence limit (97.5%)": "1995,0.37686616,0.34365577,0.41007656"
     },
     {
      "Time,Anomaly (deg C),Lower confidence limit (2.5%),Upper confidence limit (97.5%)": "1996,0.2766894,0.24318004,0.31019878"
     },
     {
      "Time,Anomaly (deg C),Lower confidence limit (2.5%),Upper confidence limit (97.5%)": "1997,0.4223085,0.39009082,0.4545262"
     },
     {
      "Time,Anomaly (deg C),Lower confidence limit (2.5%),Upper confidence limit (97.5%)": "1998,0.57731646,0.54304415,0.6115888"
     },
     {
      "Time,Anomaly (deg C),Lower confidence limit (2.5%),Upper confidence limit (97.5%)": "1999,0.32448497,0.29283476,0.35613516"
     },
     {
      "Time,Anomaly (deg C),Lower confidence limit (2.5%),Upper confidence limit (97.5%)": "2000,0.3310848,0.29822788,0.36394167"
     },
     {
      "Time,Anomaly (deg C),Lower confidence limit (2.5%),Upper confidence limit (97.5%)": "2001,0.48928034,0.4580683,0.5204924"
     },
     {
      "Time,Anomaly (deg C),Lower confidence limit (2.5%),Upper confidence limit (97.5%)": "2002,0.5434665,0.51278186,0.57415116"
     },
     {
      "Time,Anomaly (deg C),Lower confidence limit (2.5%),Upper confidence limit (97.5%)": "2003,0.5441702,0.5112426,0.5770977"
     },
     {
      "Time,Anomaly (deg C),Lower confidence limit (2.5%),Upper confidence limit (97.5%)": "2004,0.46737072,0.43433833,0.5004031"
     },
     {
      "Time,Anomaly (deg C),Lower confidence limit (2.5%),Upper confidence limit (97.5%)": "2005,0.60686255,0.5757053,0.6380198"
     },
     {
      "Time,Anomaly (deg C),Lower confidence limit (2.5%),Upper confidence limit (97.5%)": "2006,0.5725527,0.541973,0.60313237"
     },
     {
      "Time,Anomaly (deg C),Lower confidence limit (2.5%),Upper confidence limit (97.5%)": "2007,0.5917013,0.56135315,0.6220495"
     },
     {
      "Time,Anomaly (deg C),Lower confidence limit (2.5%),Upper confidence limit (97.5%)": "2008,0.46564984,0.43265733,0.49864236"
     },
     {
      "Time,Anomaly (deg C),Lower confidence limit (2.5%),Upper confidence limit (97.5%)": "2009,0.5967817,0.56525564,0.6283077"
     },
     {
      "Time,Anomaly (deg C),Lower confidence limit (2.5%),Upper confidence limit (97.5%)": "2010,0.68037146,0.649076,0.7116669"
     },
     {
      "Time,Anomaly (deg C),Lower confidence limit (2.5%),Upper confidence limit (97.5%)": "2011,0.53769773,0.5060012,0.5693943"
     },
     {
      "Time,Anomaly (deg C),Lower confidence limit (2.5%),Upper confidence limit (97.5%)": "2012,0.5776071,0.5448553,0.6103589"
     },
     {
      "Time,Anomaly (deg C),Lower confidence limit (2.5%),Upper confidence limit (97.5%)": "2013,0.6235754,0.5884838,0.6586669"
     },
     {
      "Time,Anomaly (deg C),Lower confidence limit (2.5%),Upper confidence limit (97.5%)": "2014,0.67287165,0.63890487,0.7068384"
     },
     {
      "Time,Anomaly (deg C),Lower confidence limit (2.5%),Upper confidence limit (97.5%)": "2015,0.82511437,0.79128706,0.8589417"
     },
     {
      "Time,Anomaly (deg C),Lower confidence limit (2.5%),Upper confidence limit (97.5%)": "2016,0.93292713,0.90176356,0.96409065"
     },
     {
      "Time,Anomaly (deg C),Lower confidence limit (2.5%),Upper confidence limit (97.5%)": "2017,0.84517425,0.81477475,0.87557375"
     },
     {
      "Time,Anomaly (deg C),Lower confidence limit (2.5%),Upper confidence limit (97.5%)": "2018,0.762654,0.731052,0.79425603"
     },
     {
      "Time,Anomaly (deg C),Lower confidence limit (2.5%),Upper confidence limit (97.5%)": "2019,0.8910726,0.85678726,0.92535794"
     },
     {
      "Time,Anomaly (deg C),Lower confidence limit (2.5%),Upper confidence limit (97.5%)": "2020,0.9227938,0.8882121,0.9573755"
     },
     {
      "Time,Anomaly (deg C),Lower confidence limit (2.5%),Upper confidence limit (97.5%)": "2021,0.7618559,0.72544336,0.79826844"
     },
     {
      "Time,Anomaly (deg C),Lower confidence limit (2.5%),Upper confidence limit (97.5%)": "2022,0.80128413,0.7652511,0.8373171"
     },
     {
      "Time,Anomaly (deg C),Lower confidence limit (2.5%),Upper confidence limit (97.5%)": "2023,0.7755153,0.52228117,1.0287495"
     }
    ]
    }